pyintercept/__init__.py
pyintercept/__main__.py
pyintercept/lib.py
pyintercept/handlers/__init__.py
pyintercept/handlers/json_handler.py
pyintercept/handlers/pdb_handler.py
pyintercept/handlers/pickle_handler.py
pyintercept/handlers/print_handler.py
pyintercept-0.4.1.dist-info/DESCRIPTION.rst
pyintercept-0.4.1.dist-info/METADATA
pyintercept-0.4.1.dist-info/metadata.json
pyintercept-0.4.1.dist-info/pbr.json
pyintercept-0.4.1.dist-info/RECORD
pyintercept-0.4.1.dist-info/top_level.txt
pyintercept-0.4.1.dist-info/WHEEL
