Metadata-Version: 2.0
Name: pyintercept
Version: 0.4.1
Summary: Intercept function calls from Python scripts
Home-page: http://github.com/caioariede/pyintercept
Author: Caio Ariede
Author-email: caio.ariede@gmail.com
License: MIT
Platform: any
Classifier: Intended Audience :: Developers
Classifier: Operating System :: OS Independent
Classifier: License :: OSI Approved :: MIT License
Classifier: Programming Language :: Python
Classifier: Programming Language :: Python :: 3
Classifier: Programming Language :: Python :: 3.4
Requires-Dist: byteplay
